hfc/__init__.py
hfc/version.py
hfc/fabric/__init__.py
hfc/fabric/block_decoder.py
hfc/fabric/client.py
hfc/fabric/eventhub.py
hfc/fabric/orderer.py
hfc/fabric/organization.py
hfc/fabric/peer.py
hfc/fabric/user.py
hfc/fabric/channel/__init__.py
hfc/fabric/channel/channel.py
hfc/fabric/channel/channel_configuration.py
hfc/fabric/channel/instantiation.py
hfc/fabric/channel/invocation.py
hfc/fabric/config/__init__.py
hfc/fabric/config/default.py
hfc/fabric/msp/__init__.py
hfc/fabric/transaction/__init__.py
hfc/fabric/transaction/tx_context.py
hfc/fabric/transaction/tx_proposal_request.py
hfc/fabric_ca/__init__.py
hfc/fabric_ca/caservice.py
hfc/protos/__init__.py
hfc/protos/utils.py
hfc/protos/common/__init__.py
hfc/protos/common/common_pb2.py
hfc/protos/common/common_pb2_grpc.py
hfc/protos/common/configtx_pb2.py
hfc/protos/common/configtx_pb2_grpc.py
hfc/protos/common/configuration_pb2.py
hfc/protos/common/configuration_pb2_grpc.py
hfc/protos/common/ledger_pb2.py
hfc/protos/common/ledger_pb2_grpc.py
hfc/protos/common/policies_pb2.py
hfc/protos/common/policies_pb2_grpc.py
hfc/protos/ledger/__init__.py
hfc/protos/ledger/queryresult/__init__.py
hfc/protos/ledger/queryresult/kv_query_result_pb2.py
hfc/protos/ledger/queryresult/kv_query_result_pb2_grpc.py
hfc/protos/ledger/rwset/__init__.py
hfc/protos/ledger/rwset/rwset_pb2.py
hfc/protos/ledger/rwset/rwset_pb2_grpc.py
hfc/protos/ledger/rwset/kvrwset/__init__.py
hfc/protos/ledger/rwset/kvrwset/kv_rwset_pb2.py
hfc/protos/ledger/rwset/kvrwset/kv_rwset_pb2_grpc.py
hfc/protos/msp/__init__.py
hfc/protos/msp/identities_pb2.py
hfc/protos/msp/identities_pb2_grpc.py
hfc/protos/msp/msp_principal_pb2.py
hfc/protos/msp/msp_principal_pb2_grpc.py
hfc/protos/msp/mspconfig_pb2.py
hfc/protos/msp/mspconfig_pb2_grpc.py
hfc/protos/orderer/__init__.py
hfc/protos/orderer/ab_pb2.py
hfc/protos/orderer/ab_pb2_grpc.py
hfc/protos/orderer/configuration_pb2.py
hfc_py-0.7.0.dist-info/METADATA
hfc_py-0.7.0.dist-info/RECORD
hfc_py-0.7.0.dist-info/WHEEL
hfc_py-0.7.0.dist-info/top_level.txt
