Metadata-Version: 2.1
Name: hfc-py
Version: 0.7.0
Summary: Python SDK for Hyperledger Fabric.
Home-page: https://github.com/hyperledger/fabric-sdk-py/
Author: Hyperledger Community
Author-email: UNKNOWN
License: Apache License v2.0
Download-URL: https://github.com/hyperledger/fabric-sdk-py/
Keywords: Hyperledger Fabric,SDK
Platform: any
Classifier: Development Status :: 3 - Alpha
Classifier: Environment :: Other Environment
Classifier: Intended Audience :: Developers
Classifier: Operating System :: OS Independent
Classifier: Programming Language :: Python
Classifier: Programming Language :: Python :: 2.7
Classifier: Programming Language :: Python :: 3.0
Classifier: Programming Language :: Python :: 3.5
Classifier: Topic :: Utilities
Classifier: License :: OSI Approved :: Apache Software License
Requires-Dist: cryptography (>=1.9)
Requires-Dist: grpcio (>=1.0.1)
Requires-Dist: hkdf (>=0.0.3)
Requires-Dist: pycryptodomex (>=3.4.2)
Requires-Dist: pysha3 (==1.0b1)
Requires-Dist: requests (>=2.12.4)
Requires-Dist: rx (>=1.5.3)
Requires-Dist: six (>=1.4.0)
Requires-Dist: protobuf (>=3.5.2.post1)
